Metadata-Version: 2.1
Name: phocr
Version: 1.0.3
Summary: High-Performance OCR Toolkit
Home-page: https://github.com/puhuilab/phocr
Author: PuHui Lab
Author-email: puhuilab@gmail.com
Project-URL: Bug Reports, https://github.com/puhuilab/phocr/issues
Project-URL: Source, https://github.com/puhuilab/phocr
Project-URL: Documentation, https://github.com/puhuilab/phocr#readme
Keywords: ocr,text recognition,computer vision,deep learning
Classifier: Development Status :: 4 - Beta
Classifier: Intended Audience :: Developers
Classifier: Intended Audience :: Science/Research
Classifier: License :: OSI Approved :: MIT License
Classifier: License :: Other/Proprietary License
Classifier: Operating System :: OS Independent
Classifier: Programming Language :: Python :: 3
Classifier: Programming Language :: Python :: 3.8
Classifier: Programming Language :: Python :: 3.9
Classifier: Programming Language :: Python :: 3.10
Classifier: Programming Language :: Python :: 3.11
Classifier: Programming Language :: Python :: 3.12
Classifier: Topic :: Scientific/Engineering :: Artificial Intelligence
Classifier: Topic :: Software Development :: Libraries :: Python Modules
Requires-Python: >=3.8
License-File: LICENSE
Requires-Dist: pyclipper>=1.2.0
Requires-Dist: opencv-python>=4.5.1.48
Requires-Dist: numpy<=1.26.4,>=1.19.5
Requires-Dist: six>=1.15.0
Requires-Dist: Shapely!=2.0.4,>=1.7.1
Requires-Dist: PyYAML
Requires-Dist: Pillow
Requires-Dist: tqdm
Requires-Dist: datasets
Requires-Dist: omegaconf
Requires-Dist: colorlog
Requires-Dist: onnx
Requires-Dist: Levenshtein
Requires-Dist: regex
Provides-Extra: cpu
Requires-Dist: onnxruntime>=1.20.0; extra == "cpu"
Provides-Extra: cuda
Requires-Dist: onnxruntime-gpu>=1.20.0; extra == "cuda"
Provides-Extra: dev
Requires-Dist: pytest>=6.0; extra == "dev"
Requires-Dist: pytest-cov>=2.0; extra == "dev"
Requires-Dist: black>=21.0; extra == "dev"
Requires-Dist: flake8>=3.8; extra == "dev"
Requires-Dist: mypy>=0.800; extra == "dev"
